jmcomic_api/__init__.py
jmcomic_api/__main__.py
jmcomic_api/_libs/__init__.py
jmcomic_api/_libs/jmcomic_extend_api.py
jmcomic_api/_utils/__init__.py
jmcomic_api/_utils/env.py
jmcomic_api/_utils/exception.py
jmcomic_api/_utils/file.py
jmcomic_api/_utils/other.py
jmcomic_api/core/__init__.py
jmcomic_api/core/main.py
jmcomic_api/core/routes/__init__.py
jmcomic_api/core/routes/download_lmages.py
jmcomic_api/core/routes/get_file.py
jmcomic_api/core/routes/get_raw.py
jmcomic_api/core/routes/get_raw_ranking.py
jmcomic_api/core/routes/get_raw_search.py
jmcomic_api/models/config.py
jmcomic_api/models/core/route.py
jmcomic_api-0.5.2.0.dist-info/licenses/LICENSE
jmcomic_api-0.5.2.0.dist-info/licenses/LICENSE-cn
jmcomic_api-0.5.2.0.dist-info/METADATA
jmcomic_api-0.5.2.0.dist-info/WHEEL
jmcomic_api-0.5.2.0.dist-info/entry_points.txt
jmcomic_api-0.5.2.0.dist-info/top_level.txt
jmcomic_api-0.5.2.0.dist-info/RECORD
