Metadata-Version: 2.4
Name: jmcomic_api
Version: 0.5.2.0
Summary: A Python crawler for downloading content from JMComic.
Author-email: Shua <CHA_shua@outlook.com>
Requires-Python: >=3.8
License-File: LICENSE
License-File: LICENSE-cn
Requires-Dist: fastapi>=0.115.12
Requires-Dist: jmcomic>=2.5.32
Requires-Dist: PyYAML>=6.0
Requires-Dist: uvicorn>=0.34.0
Requires-Dist: img2pdf>=0.6.0
Requires-Dist: colorlog>=6.7.0
Requires-Dist: pydantic>=2.11.0
Requires-Dist: requests>=2.32.3
Requires-Dist: pyzipper>=0.3.6
Requires-Dist: pikepdf>=9.5.2
Dynamic: license-file
